LICENSE
MANIFEST.in
README.md
requirements.txt
setup.cfg
setup.py
rcsbsearchapi/__init__.py
rcsbsearchapi/const.py
rcsbsearchapi/schema.py
rcsbsearchapi/search.py
rcsbsearchapi/update_schema.py
rcsbsearchapi.egg-info/PKG-INFO
rcsbsearchapi.egg-info/SOURCES.txt
rcsbsearchapi.egg-info/dependency_links.txt
rcsbsearchapi.egg-info/not-zip-safe
rcsbsearchapi.egg-info/requires.txt
rcsbsearchapi.egg-info/top_level.txt
rcsbsearchapi/resources/chemical_schema.json
rcsbsearchapi/resources/metadata_schema.json
tests/testschema.py
tests/testsearch.py