Metadata-Version: 2.1
Name: rcsbsearchapi
Version: 1.4.0
Summary: Python package interface for the RCSB PDB search API service
Home-page: https://github.com/rcsb/py-rcsbsearchapi
Author: Dennis Piehl
Author-email: dennis.piehl@rcsb.org
License: BSD 3-Clause
Classifier: Programming Language :: Python
Classifier: Programming Language :: Python :: 3
Classifier: Programming Language :: Python :: 3.9
Classifier: Development Status :: 4 - Beta
Classifier: Operating System :: OS Independent
Classifier: Intended Audience :: Science/Research
Classifier: Topic :: Scientific/Engineering :: Bio-Informatics
Classifier: Natural Language :: English
Classifier: License :: OSI Approved :: BSD License
Classifier: Typing :: Typed
License-File: LICENSE
Requires-Dist: requests>=2.0.0
Requires-Dist: tqdm
Provides-Extra: dev
Requires-Dist: check-manifest; extra == "dev"
Provides-Extra: test
Requires-Dist: coverage; extra == "test"
Provides-Extra: tests
Requires-Dist: tox; extra == "tests"
Requires-Dist: pylint; extra == "tests"
Requires-Dist: black>=21.5b1; extra == "tests"
Requires-Dist: flake8; extra == "tests"
Provides-Extra: progressbar
Requires-Dist: tqdm; extra == "progressbar"
Provides-Extra: docs
Requires-Dist: sphinx; extra == "docs"
Requires-Dist: sphinx-rtd-theme; extra == "docs"
Requires-Dist: myst-parser; extra == "docs"
